heartbeat_client/__init__.py
heartbeat_client/main.py
heartbeat_client-0.7.0.dist-info/METADATA
heartbeat_client-0.7.0.dist-info/WHEEL
heartbeat_client-0.7.0.dist-info/entry_points.txt
heartbeat_client-0.7.0.dist-info/top_level.txt
heartbeat_client-0.7.0.dist-info/RECORD
